setup.py
hometrainer/__init__.py
hometrainer/agents.py
hometrainer/config.py
hometrainer/core.py
hometrainer/distribution.py
hometrainer/executors.py
hometrainer/neural_network.py
hometrainer/util.py
hometrainer.egg-info/PKG-INFO
hometrainer.egg-info/SOURCES.txt
hometrainer.egg-info/dependency_links.txt
hometrainer.egg-info/not-zip-safe
hometrainer.egg-info/requires.txt
hometrainer.egg-info/top_level.txt