Metadata-Version: 1.0
Name: hometrainer
Version: 0.1.2
Summary: Simple AlphaZero implementation
Home-page: https://github.com/FritzFlorian/hometrainer
Author: Fritz Florian
Author-email: UNKNOWN
License: MIT
Platform: UNKNOWN
